odoo/addons/website_sale_attribute_filter_order/README.rst
odoo/addons/website_sale_attribute_filter_order/__init__.py
odoo/addons/website_sale_attribute_filter_order/__manifest__.py
odoo/addons/website_sale_attribute_filter_order/i18n/ca.po
odoo/addons/website_sale_attribute_filter_order/i18n/es.po
odoo/addons/website_sale_attribute_filter_order/i18n/website_sale_attribute_filter_order.pot
odoo/addons/website_sale_attribute_filter_order/readme/CONFIGURE.rst
odoo/addons/website_sale_attribute_filter_order/readme/CONTRIBUTORS.rst
odoo/addons/website_sale_attribute_filter_order/readme/DESCRIPTION.rst
odoo/addons/website_sale_attribute_filter_order/readme/ROADMAP.rst
odoo/addons/website_sale_attribute_filter_order/readme/USAGE.rst
odoo/addons/website_sale_attribute_filter_order/static/description/icon.png
odoo/addons/website_sale_attribute_filter_order/static/description/index.html
odoo/addons/website_sale_attribute_filter_order/templates/website_sale.xml
odoo13_addon_website_sale_attribute_filter_order-13.0.1.0.1.dev7.dist-info/METADATA
odoo13_addon_website_sale_attribute_filter_order-13.0.1.0.1.dev7.dist-info/WHEEL
odoo13_addon_website_sale_attribute_filter_order-13.0.1.0.1.dev7.dist-info/top_level.txt
odoo13_addon_website_sale_attribute_filter_order-13.0.1.0.1.dev7.dist-info/RECORD
